README.md
setup.py
terraecs/__init__.py
terraecs/__main__.py
terraecs.egg-info/PKG-INFO
terraecs.egg-info/SOURCES.txt
terraecs.egg-info/dependency_links.txt
terraecs.egg-info/entry_points.txt
terraecs.egg-info/requires.txt
terraecs.egg-info/top_level.txt