Metadata-Version: 2.1
Name: terraecs
Version: 0.0.3
Summary: A simple Fargate after Terraform runner.
Home-page: https://github.com/lifeofguenter/terraecs
Author: Gunter Grodotzki
Author-email: gunter@grodotzki.co.za
License: UNKNOWN
Platform: UNKNOWN
Classifier: Programming Language :: Python :: 3
Classifier: License :: OSI Approved :: GNU General Public License v3 or later (GPLv3+)
Classifier: Operating System :: OS Independent
Requires-Python: >=3
